mupny/__init__.py
mupny/__main__.py
mupny/a.py
mupny/b.py
mupny/data/data.txt
mupny/data/mupny2-4/main_ac3.py
mupny/data/mupny2-4/main_australia.py
mupny/data/mupny2-4/main_containers.py
mupny/data/mupny2-4/main_cruciverba.py
mupny/data/mupny2-4/main_game.py
mupny/data/mupny2-4/main_hanoi.py
mupny/data/mupny2-4/main_monkAI.py
mupny/data/mupny2-4/main_pacman.py
mupny/data/mupny2-4/main_queens.py
mupny/data/mupny2-4/main_streets.py
mupny/data/mupny2-4/main_tictactoe.py
mupny/data/mupny2-4/csp/__init__.py
mupny/data/mupny2-4/csp/ac3.py
mupny/data/mupny2-4/csp/backtracking.py
mupny/data/mupny2-4/csp/backtracking2.py
mupny/data/mupny2-4/csp/constraints.py
mupny/data/mupny2-4/csp/problem.py
mupny/data/mupny2-4/csp/__pycache__/__init__.cpython-312.pyc
mupny/data/mupny2-4/csp/__pycache__/ac3.cpython-312.pyc
mupny/data/mupny2-4/csp/__pycache__/backtracking.cpython-312.pyc
mupny/data/mupny2-4/csp/__pycache__/constraints.cpython-312.pyc
mupny/data/mupny2-4/csp/__pycache__/problem.cpython-312.pyc
mupny/data/mupny2-4/game/__init__.py
mupny/data/mupny2-4/game/games.py
mupny/data/mupny2-4/game/player.py
mupny/data/mupny2-4/game/search.py
mupny/data/mupny2-4/game/search2.py
mupny/data/mupny2-4/game/__pycache__/__init__.cpython-312.pyc
mupny/data/mupny2-4/game/__pycache__/games.cpython-312.pyc
mupny/data/mupny2-4/game/__pycache__/player.cpython-312.pyc
mupny/data/mupny2-4/game/__pycache__/search.cpython-312.pyc
mupny/data/mupny2-4/input/cruciverba-10-2023.png
mupny/data/mupny2-4/input/cruciverba-local-search-10-2023.png
mupny/data/mupny2-4/input/italian.txt
mupny/data/mupny2-4/input/roads.py
mupny/data/mupny2-4/input/words.py
mupny/data/mupny2-4/input/__pycache__/roads.cpython-312.pyc
mupny/data/mupny2-4/input/__pycache__/roads.cpython-39.pyc
mupny/data/mupny2-4/input/__pycache__/words.cpython-312.pyc
mupny/data/mupny2-4/prolog/__init__.py
mupny/data/mupny2-4/prolog/exercise.pl
mupny/data/mupny2-4/src/GraphSearch.py
mupny/data/mupny2-4/src/Node.py
mupny-1.3.dist-info/METADATA
mupny-1.3.dist-info/WHEEL
mupny-1.3.dist-info/top_level.txt
mupny-1.3.dist-info/RECORD
