Metadata-Version: 2.1
Name: mupny
Version: 1.3
Summary: simplest example in the python world
License: MIT
